diff_robot_data/2link_robot.urdf
diff_robot_data/__init__.py
diff_robot_data/allegro/meshes/base_link.STL
diff_robot_data/allegro/meshes/base_link_left.STL
diff_robot_data/allegro/meshes/link_0.0.STL
diff_robot_data/allegro/meshes/link_1.0.STL
diff_robot_data/allegro/meshes/link_12.0_left.STL
diff_robot_data/allegro/meshes/link_12.0_right.STL
diff_robot_data/allegro/meshes/link_13.0.STL
diff_robot_data/allegro/meshes/link_14.0.STL
diff_robot_data/allegro/meshes/link_15.0.STL
diff_robot_data/allegro/meshes/link_15.0_tip.STL
diff_robot_data/allegro/meshes/link_2.0.STL
diff_robot_data/allegro/meshes/link_3.0.STL
diff_robot_data/allegro/meshes/link_3.0_tip.STL
diff_robot_data/allegro/meshes/link_4.0.STL
diff_robot_data/allegro/urdf/allegro_hand_description_left.urdf
diff_robot_data/allegro/urdf/allegro_hand_description_left_small_damping.urdf
diff_robot_data/fetch_description/meshes/base_link.dae
diff_robot_data/fetch_description/meshes/base_link_collision.STL
diff_robot_data/fetch_description/meshes/base_link_uv.png
diff_robot_data/fetch_description/meshes/bellows_link.STL
diff_robot_data/fetch_description/meshes/bellows_link_collision.STL
diff_robot_data/fetch_description/meshes/elbow_flex_link.dae
diff_robot_data/fetch_description/meshes/elbow_flex_link_collision.STL
diff_robot_data/fetch_description/meshes/elbow_flex_uv.png
diff_robot_data/fetch_description/meshes/estop_link.STL
diff_robot_data/fetch_description/meshes/forearm_roll_link.dae
diff_robot_data/fetch_description/meshes/forearm_roll_link_collision.STL
diff_robot_data/fetch_description/meshes/forearm_roll_uv.png
diff_robot_data/fetch_description/meshes/gripper_link.STL
diff_robot_data/fetch_description/meshes/gripper_link.dae
diff_robot_data/fetch_description/meshes/gripper_uv.png
diff_robot_data/fetch_description/meshes/head_pan_link.dae
diff_robot_data/fetch_description/meshes/head_pan_link_collision.STL
diff_robot_data/fetch_description/meshes/head_pan_uv.png
differentiable_robot_model-0.2.3.dist-info/LICENSE
differentiable_robot_model-0.2.3.dist-info/METADATA
differentiable_robot_model-0.2.3.dist-info/WHEEL
differentiable_robot_model-0.2.3.dist-info/top_level.txt
differentiable_robot_model-0.2.3.dist-info/RECORD
