Metadata-Version: 2.1
Name: differentiable-robot-model
Version: 0.2.3
Summary: A pytorch library that implements differentiable and learnable robot models, which allows users to learn parameters of analytical robot models, and/or propagate gradients through analytical robot computations such as forward kinematics.
Home-page: https://github.com/facebookresearch/differentiable-robot-model
Author: Franziska Meier
Author-email: fmeier@fb.com
License: MIT
Keywords: robotics,differentiable,optimization
Platform: UNKNOWN
Classifier: Programming Language :: Python
Classifier: Programming Language :: Python :: 3
Requires-Python: >=3.6.0
License-File: LICENSE
Requires-Dist: torch (>=1.6)
Requires-Dist: pyquaternion (>=0.9.9)
Requires-Dist: hydra-core (>=1.0.3)
Requires-Dist: urdf-parser-py (>=0.0.3)
Requires-Dist: Sphinx (>=3.5.4)
Requires-Dist: recommonmark (>=0.7.1)
